{
  "topicSlug": "invitados",
  "generatedAt": "2026-07-07T07:29:54.689Z",
  "claims": [
    {
      "id": "invitados-guests_allowed",
      "statement": "Las personas socias pueden invitar a terceros a las instalaciones",
      "evidenceType": "weak_evidence",
      "confidence": "low",
      "supportingReferences": [
        "docs-otros-modelo-estatutos-viviendas",
        "docs-estatutos-estatutos-elciempies",
        "docs-estatutos-estatutos-los-girasoles"
      ],
      "explanation": "Solo 3 referencia(s) en 3 proyecto(s), y ninguna contiene evidencia suficiente."
    },
    {
      "id": "invitados-notice",
      "statement": "La persona socia debe avisar o solicitar autorización para invitar",
      "evidenceType": "weak_evidence",
      "confidence": "low",
      "supportingReferences": [],
      "explanation": "No se ha encontrado evidencia documental que respalde: \"La persona socia debe avisar o solicitar autorización para invitar\". Puede estar resolviéndose informalmente o no estar documentado en las fuentes analizadas."
    },
    {
      "id": "invitados-guest_limit",
      "statement": "Existe un límite de noches o estancias para personas invitadas",
      "evidenceType": "weak_evidence",
      "confidence": "low",
      "supportingReferences": [],
      "explanation": "No se ha encontrado evidencia documental que respalde: \"Existe un límite de noches o estancias para personas invitadas\". Puede estar resolviéndose informalmente o no estar documentado en las fuentes analizadas."
    },
    {
      "id": "invitados-guest_responsibility",
      "statement": "La persona socia es responsable de los daños causados por sus invitados",
      "evidenceType": "weak_evidence",
      "confidence": "low",
      "supportingReferences": [],
      "explanation": "No se ha encontrado evidencia documental que respalde: \"La persona socia es responsable de los daños causados por sus invitados\". Puede estar resolviéndose informalmente o no estar documentado en las fuentes analizadas."
    },
    {
      "id": "invitados-guest_common_spaces",
      "statement": "Las personas invitadas pueden usar espacios comunes",
      "evidenceType": "weak_evidence",
      "confidence": "low",
      "supportingReferences": [],
      "explanation": "No se ha encontrado evidencia documental que respalde: \"Las personas invitadas pueden usar espacios comunes\". Puede estar resolviéndose informalmente o no estar documentado en las fuentes analizadas."
    },
    {
      "id": "invitados-guest_alone",
      "statement": "Personas invitadas pueden estar sin la persona socia presente",
      "evidenceType": "weak_evidence",
      "confidence": "low",
      "supportingReferences": [],
      "explanation": "No se ha encontrado evidencia documental que respalde: \"Personas invitadas pueden estar sin la persona socia presente\". Puede estar resolviéndose informalmente o no estar documentado en las fuentes analizadas."
    }
  ],
  "conflictingApproaches": [],
  "evidenceSummary": {
    "totalClaims": 6,
    "explicitCount": 0,
    "inferredCount": 0,
    "recommendationCount": 0,
    "weakEvidenceCount": 6,
    "conflictingCount": 0,
    "highConfidenceCount": 0,
    "mediumConfidenceCount": 0,
    "lowConfidenceCount": 6
  },
  "extracts": [
    {
      "id": "invitados-guests_allowed-docs-otros-modelo-estatutos-viviendas-229",
      "claimId": "invitados-guests_allowed",
      "documentSlug": "docs-otros-modelo-estatutos-viviendas",
      "documentTitle": "MODELO ESTATUTOS VIVIENDAS",
      "documentType": "otro",
      "sourcePath": "docs/otros/MODELO ESTATUTOS  VIVIENDAS.pdf",
      "articleOrSection": "3. Si la Cooperativa realizara operaciones con terceras personas prescindiendo de lo anteriormente",
      "snippet": "3. Si la Cooperativa realizara operaciones con terceras personas prescindiendo de lo anteriormente previsto, cualquier persona socia expectante o, en su defecto, incluida en el listado de personas solicitantes de vivienda o locales en régimen cooperativo, podrá ejercitar el derecho de retracto, debiendo reembolsar a la persona compradora la cantidad desembolsada incrementada con la revalorización que haya experimentado, conforme al índice de precios al consumo, durante el período comprendido entre las fechas de los distintos desembolsos parciales y la fecha de la transmisión de los derechos sobre la vivienda o local, además de los gastos a que se refiere el apartado 2 del artículo 1518 del CC; si bien el reembolso a la persona compradora de los gastos referidos en el apartado 1 del aludido...",
      "score": 3,
      "relevanceFactors": {
        "explicit": false,
        "headingRelevant": false,
        "contextualCooccurrence": false,
        "topicDensity": false,
        "conceptProximity": false
      }
    },
    {
      "id": "invitados-guests_allowed-docs-estatutos-estatutos-elciempies-102",
      "claimId": "invitados-guests_allowed",
      "documentSlug": "docs-estatutos-estatutos-elciempies",
      "documentTitle": "Estatutos Elciempies",
      "documentType": "estatutos",
      "sourcePath": "docs/estatutos/estatutos_elciempies.pdf",
      "articleOrSection": "c) Revocación de los cargos sociales antes mencionados.",
      "snippet": "c) Revocación de los cargos sociales antes mencionados. Ar\u001aculo 29.- Impugnación de acuerdos de la Asamblea General. 1.- Los acuerdos de la Asamblea General que sean contrarios a la Ley, que se opongan a estos estatutos o lesionen, en bene,cio de una o varias personas socias o de terceras personas, los intereses de la coopera\u000eva, podrán ser impugnados según las normas y dentro de los plazos establecidos en la Ley. No procederá la impugnación de un acuerdo social que haya sido dejado sin efecto o sus\u000etuido válidamente por otro. 2.- Serán nulos los acuerdos contrarios a la Ley; los demás acuerdos serán anulables. 3.- La acción de impugnación de los acuerdos nulos caducará en el plazo de un año, con excepción de los acuerdos que, por su causa o contenido, resulten contrarios al orden público....",
      "score": 3,
      "relevanceFactors": {
        "explicit": false,
        "headingRelevant": false,
        "contextualCooccurrence": false,
        "topicDensity": false,
        "conceptProximity": false
      }
    },
    {
      "id": "invitados-guests_allowed-docs-estatutos-estatutos-los-girasoles-107",
      "claimId": "invitados-guests_allowed",
      "documentSlug": "docs-estatutos-estatutos-los-girasoles",
      "documentTitle": "Estatutos Los Girasoles",
      "documentType": "estatutos",
      "sourcePath": "docs/estatutos/estatutos_los_girasoles.pdf",
      "articleOrSection": "c) Revocación de los cargos sociales antes mencionados.",
      "snippet": "c) Revocación de los cargos sociales antes mencionados. Arơculo 32.- Impugnación de acuerdos de la Asamblea General. 1.- Los acuerdos de la Asamblea General que sean contrarios a la Ley, que se opongan a estos estatutos o lesionen, en beneficio de una o varias personas socias o de terceras personas, los intereses de la cooperaƟva, podrán ser impugnados según las normas y dentro de los plazos establecidos en la Ley. No procederá la impugnación de un acuerdo social que haya sido dejado sin efecto o susƟtuido válidamente por otro. 2.- Serán nulos los acuerdos contrarios a la Ley; los demás acuerdos serán anulables. 3.- La acción de impugnación de los acuerdos nulos caducará en el plazo de un año, con excepción de los acuerdos que, por su causa o contenido, resulten contrarios al orden público...",
      "score": 3,
      "relevanceFactors": {
        "explicit": false,
        "headingRelevant": false,
        "contextualCooccurrence": false,
        "topicDensity": false,
        "conceptProximity": false
      }
    }
  ],
  "nonSubstantiveFiltered": 3,
  "evidenceHealth": "insufficient"
}
